MANIFEST.in
setup.py
versiontools_support.py
sigintwrap/__init__.py
sigintwrap/sigintwrap.py
sigintwrap.egg-info/PKG-INFO
sigintwrap.egg-info/SOURCES.txt
sigintwrap.egg-info/dependency_links.txt
sigintwrap.egg-info/entry_points.txt
sigintwrap.egg-info/top_level.txt