Metadata-Version: 1.0
Name: sigintwrap
Version: 0.0.2
Summary: Wrapper to forward TERM signals to INT signals so uWSGI plays nice with runit
Home-page: https://globusonline.github.com/sigint
Author: Josh Bryan
Author-email: jbryan@ci.uchicago.edu
License: UNKNOWN
Platform: UNKNOWN
Classifier: Programming Language :: Python :: 2
